creon_api/__init__.py
creon_api/config.py
creon_api/cybos.py
creon_api/logger.py
creon_api/utils.py
creon_api/scripts/__init__.py
creon_api/scripts/crawl_code_list.py
creon_api/scripts/crawl_daily_minute_price.py
creon_api/scripts/crawl_daily_price.py
creon_api/scripts/crawl_daily_stock_adj_info.py
creon_api/scripts/parse_adj_ratio.py
creon_api/scripts/processing_adj_info.py
creon_api-1.1.dist-info/METADATA
creon_api-1.1.dist-info/WHEEL
creon_api-1.1.dist-info/top_level.txt
creon_api-1.1.dist-info/RECORD
