Metadata-Version: 2.1
Name: creon-api
Version: 1.1
Summary: daishin creon api
Home-page: https://github.com/quantrading/creon-api
Author: Jang Woo Jae
Author-email: wojae.jang@gmail.com
License: MIT
Platform: UNKNOWN
Requires-Python: >=3
Requires-Dist: pandas
Requires-Dist: pywin32
